.gitignore
.pre-commit-config.yaml
.pylintrc
.readthedocs.yaml
CODE_OF_CONDUCT.md
LICENSE
README.rst
README.rst.license
pyproject.toml
requirements.txt
setup.py
sparkfun_qwiickeypad.py
.github/PULL_REQUEST_TEMPLATE/adafruit_circuitpython_pr.md
.github/workflows/build.yml
.github/workflows/failure-help-text.yml
.github/workflows/release.yml
LICENSES/CC-BY-4.0.txt
LICENSES/MIT.txt
LICENSES/Unlicense.txt
docs/api.rst
docs/api.rst.license
docs/conf.py
docs/examples.rst
docs/examples.rst.license
docs/index.rst
docs/index.rst.license
docs/requirements.txt
docs/_static/favicon.ico
docs/_static/favicon.ico.license
examples/example1_read_button.py
examples/example2_read_with_time.py
examples/example3_change_i2c_address.py
examples/example4_i2c_scanner.py
examples/example5_interrupt_read.py
examples/example6_key_code.py
examples/qwiickeypad_simpletest.py
sparkfun_circuitpython_qwiickeypad.egg-info/PKG-INFO
sparkfun_circuitpython_qwiickeypad.egg-info/SOURCES.txt
sparkfun_circuitpython_qwiickeypad.egg-info/dependency_links.txt
sparkfun_circuitpython_qwiickeypad.egg-info/requires.txt
sparkfun_circuitpython_qwiickeypad.egg-info/top_level.txt