Metadata-Version: 2.1
Name: sparkfun-circuitpython-qwiickeypad
Version: 1.0.3
Summary: CircuitPython library for the Sparkfun Qwiic Keypad
Home-page: https://github.com/fourstix/Sparkfun_CircuitPython_QwiicKeypad.git
Author: Gaston Williams
Author-email: fourstix@gmail.com
License: MIT
Keywords: adafruit blinka circuitpython micropython qwiickeypad sparkfun qwiic keypad
Platform: UNKNOWN
Classifier: Development Status :: 3 - Alpha
Classifier: Intended Audience :: Developers
Classifier: Topic :: Software Development :: Libraries
Classifier: Topic :: System :: Hardware
Classifier: License :: OSI Approved :: MIT License
Classifier: Programming Language :: Python :: 3
Classifier: Programming Language :: Python :: 3.4
Classifier: Programming Language :: Python :: 3.5
License-File: LICENSE
